tools/__init__.py
tools/videregaande.py
vgstools-0.2.dist-info/LICENSE
vgstools-0.2.dist-info/METADATA
vgstools-0.2.dist-info/WHEEL
vgstools-0.2.dist-info/top_level.txt
vgstools-0.2.dist-info/RECORD
