Metadata-Version: 2.1
Name: vgstools
Version: 0.2
Summary: A collection of the tools I made in my first year
Home-page: https://github.com/Enderz420/vgstools
Author: Enderz
License: MIT
Classifier: Programming Language :: Python :: 3
Classifier: License :: OSI Approved :: MIT License
Classifier: Operating System :: OS Independent
Requires-Python: >=3.6
License-File: LICENSE
